ctadl_jadx_fact_generator_plugin/VERSION
ctadl_jadx_fact_generator_plugin/__init__.py
ctadl_jadx_fact_generator_plugin/ctadl-jadx-fact-generator.jar
ctadl_jadx_fact_generator_plugin-0.6.2.dist-info/METADATA
ctadl_jadx_fact_generator_plugin-0.6.2.dist-info/WHEEL
ctadl_jadx_fact_generator_plugin-0.6.2.dist-info/top_level.txt
ctadl_jadx_fact_generator_plugin-0.6.2.dist-info/RECORD
