Metadata-Version: 2.1
Name: ctadl-jadx-fact-generator-plugin
Version: 0.6.2
Summary: CTADL JADX fact generator plugin
Home-page: https://github.com/sandialabs/ctadl-jadx-fact-generator
Project-URL: Bug Tracker, https://github.com/sandialabs/ctadl-jadx-fact-generator/issues
Classifier: Programming Language :: Python :: 3.9
Classifier: Environment :: Console
Classifier: Environment :: Plugins
Classifier: License :: OSI Approved :: Apache Software License
Classifier: Operating System :: POSIX
Requires-Python: >=3.9
